abs_imports.py
absolufy_imports.py
absolufy_imports-0.3.1.dist-info/LICENSE
absolufy_imports-0.3.1.dist-info/METADATA
absolufy_imports-0.3.1.dist-info/WHEEL
absolufy_imports-0.3.1.dist-info/entry_points.txt
absolufy_imports-0.3.1.dist-info/top_level.txt
absolufy_imports-0.3.1.dist-info/RECORD
